yadc/__init__.py
yadc/browser.py
yadc/cli.py
yadc/humanlike.py
yadc/scraper.py
yadc/undetected_browser.py
yadc/utils.py
yadc-0.18.0.dist-info/entry_points.txt
yadc-0.18.0.dist-info/LICENSE
yadc-0.18.0.dist-info/WHEEL
yadc-0.18.0.dist-info/METADATA
yadc-0.18.0.dist-info/RECORD
