Metadata-Version: 2.1
Name: yadc
Version: 0.18.0
Summary: Yet Another DVSA Cancellation checker
License: MIT
Author: John Maximilian
Author-email: 2e0byo@gmail.com
Requires-Python: >=3.9,<3.11
Classifier: License :: OSI Approved :: MIT License
Classifier: Programming Language :: Python :: 3
Classifier: Programming Language :: Python :: 3.10
Classifier: Programming Language :: Python :: 3.9
Requires-Dist: coloredlogs (>=15.0.1,<16.0.0)
Requires-Dist: fake-useragent (>=0.1.11,<0.2.0)
Requires-Dist: halo (>=0.0.31,<0.0.32)
Requires-Dist: numpy (>=1.21.4,<2.0.0)
Requires-Dist: psutil (>=5.8.0,<6.0.0)
Requires-Dist: pydantic (>=1.8.2,<2.0.0)
Requires-Dist: selenium (>=4.0.0,<5.0.0)
Requires-Dist: undetected-chromedriver (>=3.1.3,<4.0.0)
